[{"type": "samples", "id": "SRS1791805", "attributes": {"sample-metadata": [{"key": "geographic location (longitude)", "value": "138.83", "unit": null}, {"key": "geographic location (country and/or sea,region)", "value": "Japan", "unit": null}, {"key": "collection date", "value": "2015-02-05", "unit": null}, {"key": "geographic location (latitude)", "value": "37.43", "unit": null}, {"key": "instrument model", "value": "Illumina HiSeq 2500", "unit": null}, {"key": "last update date", "value": "2016-11-10", "unit": null}], "longitude": 138.83, "biosample": "SAMN05720199", "latitude": 37.43, "accession": "SRS1791805", "analysis-completed": "2018-10-25", "collection-date": "2015-02-05", "geo-loc-name": "Japan", "sample-desc": "Active sludge microbial communities of municipal wastewater-treating anaerobic digesters from Japan - AD_JPNNA6_MetaG", "environment-biome": null, "environment-feature": null, "environment-material": null, "sample-name": "Gp0138808", "sample-alias": "Gp0138808", "host-tax-id": null, "species": null, "last-update": "2018-10-25T20:56:15"}, "relationships": {"studies": {"links": {"related": "https://www.ebi.ac.uk/metagenomics/api/v1/samples/SRS1791805/studies"}, "data": [{"type": "studies", "id": "MGYS00003413", "links": {"self": "https://www.ebi.ac.uk/metagenomics/api/v1/studies/MGYS00003413"}}]}, "biome": {"data": {"type": "biomes", "id": "root:Engineered:Wastewater:Activated Sludge"}, "links": {"related": "https://www.ebi.ac.uk/metagenomics/api/v1/biomes/root:Engineered:Wastewater:Activated%20Sludge"}}, "runs": {"links": {"related": "https://www.ebi.ac.uk/metagenomics/api/v1/samples/SRS1791805/runs"}}}, "links": {"self": "https://www.ebi.ac.uk/metagenomics/api/v1/samples/SRS1791805"}}]